Workbook

Sheet Orders
A1: Date | B1: Customer Name | C1: Phone | D1: Source | E1: UTM Campaign | F1: Product | G1: Quantity | H1: Price | I1: Payment Mode | J1: Delivery Area | K1: Dietary Note | L1: New or Repeat | M1: Referral By | N1: Notes
A2: 2026-07-07 | B2: Example Customer | C2: +91-98765-43210 | D2: Instagram Story | E2: daily_thali_july7 | F2: Today's Thali | G2: 1 | H2: 220 | I2: UPI | J2: Auroville Central | K2: No onion-garlic | L2: New | N2: First order from IG
A3: 2026-07-07 | B3: Example Customer 2 | C3: +91-98765-43211 | D3: WhatsApp Broadcast | E3: weekly_tiffin | F3: Weekly Tiffin | G3: 1 | H3: 1100 | I3: Cash | J3: Verite | K3: Gluten-free | L3: New | N3: New subscriber
A4: 2026-07-08 | B4: Example Customer 3 | C4: +91-98765-43212 | D4: Guesthouse Flyer | E4: newcomer_pack | F4: Newcomer Starter Pack | G4: 1 | H4: 1200 | I4: UPI | J4: Gaia Guesthouse | K4: Vegan | L4: New | M4: Guesthouse manager referral

Sheet Content Calendar
A1: Date | B1: Platform | C1: Post Type | D1: Content | E1: Link / UTM | F1: Reach | G1: Link Clicks | H1: WhatsApp Inquiries | I1: Orders | J1: Revenue | K1: Notes
A2: 2026-07-07 | B2: Instagram | C2: Story | D2: Daily thali photo — palak paneer | E2: https://bit.ly/ritu_thali_july7 | F2: 120 | G2: 15 | H2: 4 | I2: 2 | J2: 440 | K2: Good engagement
A3: 2026-07-07 | B3: WhatsApp | C3: Broadcast | D3: Morning menu + pre-book CTA | E3: wa.me link | F3: 80 | G3: 22 | H3: 6 | I3: 3 | J3: 660 | K3: Best conversion day
A4: 2026-07-08 | B4: Instagram | C4: Reel | D4: Kitchen packing timelapse | E4: https://bit.ly/ritu_reel_july8 | F4: 450 | G4: 35 | H4: 8 | I4: 2 | J4: 440 | K4: Reel got high reach but lower conversion

Sheet Inferred Segments
A1: Phone | B1: Name | C1: Total Orders | D1: Total Spent (₹) | E1: Avg Order Value (₹) | F1: First Order Date | G1: Last Order Date | H1: Days Since Last Order | I1: Resident Type (Inferred) | J1: Family Size (Inferred) | K1: Subscriber | L1: Regular | M1: High Value | N1: Dormant | O1: Wellness Customer | P1: Advocate | Q1: Preferred Meal | R1: Preferred Product
A2: Sample Phone | B2: Sample Name | C2: =COUNTIF(Orders!C:C,A2) | D2: =SUMIF(Orders!C:C,A2,Orders!H:H) | E2: =IFERROR(C2/D2,0) | F2: =MINIFS(Orders!A:A,Orders!C:C,A2) | G2: =MAXIFS(Orders!A:A,Orders!C:C,A2) | H2: =TODAY()-G2 | I2: =IF(D2>=15,"Long-term Resident",IF(D2>=3,"Newcomer/Volunteer","Visitor")) | J2: =IF(COUNTIFS(Orders!C:C,A2,Orders!G:G,">1")>=3,"Family","Single/Couple") | K2: =IF(COUNTIFS(Orders!C:C,A2,Orders!F:F,"Weekly Tiffin")>0,"Yes","No") | L2: =IF(D2>=3,"Yes","No") | M2: =IF(E2>=2500,"Yes","No") | N2: =IF(H2>30,"Yes","No") | O2: =IF(COUNTIFS(Orders!C:C,A2,Orders!F:F,"Wellness Thali")>0,"Yes","No") | P2: =IF(M2="Yes","Yes","No") | Q2: =IF(COUNTIFS(Orders!C:C,A2,Orders!F:F,"*Dinner*")>COUNTIFS(Orders!C:C,A2,Orders!F:F,"*Lunch*"),"Dinner","Lunch") | R2: =INDEX(Orders!F:F,MATCH(A2,Orders!C:C,0))

Sheet Monthly KPI Dashboard
A1: Metric | B1: January | C1: February | D1: March | E1: Target | F1: How to Calculate
A2: Website visitors | B2: 0 | C2: 0 | D2: 0 | E2: 500 | F2: Google Analytics 4
A3: WhatsApp inquiries | B3: 0 | C3: 0 | D3: 0 | E3: 60 | F3: Count from order log
A4: Inquiry to order conversion rate (%) | B4: 0 | C4: 0 | D4: 0 | E4: 40 | F4: Orders / Inquiries x 100
A5: New customers | B5: 0 | C5: 0 | D5: 0 | E5: 25 | F5: Unique first-time customers in order log
A6: Repeat customers (%) | B6: 0 | C6: 0 | D6: 0 | E6: 45 | F6: Repeat customers / Total customers x 100
A7: Google reviews | B7: 0 | C7: 0 | D7: 0 | E7: 50 | F7: Google Business Profile
A8: Instagram followers | B8: 0 | C8: 0 | D8: 0 | E8: 500 | F8: Instagram Insights
A9: Weekly tiffin subscribers | B9: 0 | C9: 0 | D9: 0 | E9: 25 | F9: Order log product = Weekly Tiffin
A10: Average order value (₹) | B10: 0 | C10: 0 | D10: 0 | E10: 320 | F10: Total revenue / Total orders
A11: Total revenue (₹) | B11: 0 | C11: 0 | D11: 0 | E11: 50000 | F11: Sum of Price column
A12: Cost per new customer (₹) | B12: 0 | C12: 0 | D12: 0 | E12: 0 | F12: Total marketing spend / New customers
A13: Top performing source | B13: - | C13: - | D13: - | E13: - | F13: Filter order log by Source
A14: Top performing product | B14: - | C14: - | D14: - | E14: - | F14: Filter order log by Product

Sheet Source Analysis
A1: Source | B1: Total Orders | C1: Total Revenue | D1: New Customers | E1: Repeat Customers | F1: Avg Order Value
A2: Instagram Story | B2: =COUNTIF(Orders!D:D,"Instagram Story") | C2: =SUMIF(Orders!D:D,"Instagram Story",Orders!H:H) | D2: =COUNTIFS(Orders!D:D,"Instagram Story",Orders!L:L,"New") | E2: =COUNTIFS(Orders!D:D,"Instagram Story",Orders!L:L,"Repeat") | F2: =IFERROR(C2/B2,0)
A3: WhatsApp Broadcast | B3: =COUNTIF(Orders!D:D,"WhatsApp Broadcast") | C3: =SUMIF(Orders!D:D,"WhatsApp Broadcast",Orders!H:H) | D3: =COUNTIFS(Orders!D:D,"WhatsApp Broadcast",Orders!L:L,"New") | E3: =COUNTIFS(Orders!D:D,"WhatsApp Broadcast",Orders!L:L,"Repeat") | F3: =IFERROR(C3/B3,0)
A4: Guesthouse Flyer | B4: =COUNTIF(Orders!D:D,"Guesthouse Flyer") | C4: =SUMIF(Orders!D:D,"Guesthouse Flyer",Orders!H:H) | D4: =COUNTIFS(Orders!D:D,"Guesthouse Flyer",Orders!L:L,"New") | E4: =COUNTIFS(Orders!D:D,"Guesthouse Flyer",Orders!L:L,"Repeat") | F4: =IFERROR(C4/B4,0)
A5: Google Business | B5: =COUNTIF(Orders!D:D,"Google Business") | C5: =SUMIF(Orders!D:D,"Google Business",Orders!H:H) | D5: =COUNTIFS(Orders!D:D,"Google Business",Orders!L:L,"New") | E5: =COUNTIFS(Orders!D:D,"Google Business",Orders!L:L,"Repeat") | F5: =IFERROR(C5/B5,0)

Sheet Product Analysis
A1: Product | B1: Orders | C1: Revenue | D1: Avg Price
A2: Today's Thali | B2: =COUNTIF(Orders!F:F,"Today's Thali") | C2: =SUMIF(Orders!F:F,"Today's Thali",Orders!H:H) | D2: =IFERROR(C2/B2,0)
A3: Weekly Tiffin | B3: =COUNTIF(Orders!F:F,"Weekly Tiffin") | C3: =SUMIF(Orders!F:F,"Weekly Tiffin",Orders!H:H) | D3: =IFERROR(C3/B3,0)
A4: Wellness Thali | B4: =COUNTIF(Orders!F:F,"Wellness Thali") | C4: =SUMIF(Orders!F:F,"Wellness Thali",Orders!H:H) | D4: =IFERROR(C4/B4,0)
A5: Family Thali | B5: =COUNTIF(Orders!F:F,"Family Thali") | C5: =SUMIF(Orders!F:F,"Family Thali",Orders!H:H) | D5: =IFERROR(C5/B5,0)

Sheet Weekly Review
A1: Week | B1: Total Orders | C1: Revenue | D1: New Customers | E1: Repeat Customers | F1: Top Source | G1: Top Product | H1: Experiment | I1: Result | J1: Next Week Action

Sheet Customer List
A1: Phone | B1: Name | C1: Area | D1: Accommodation Type | E1: Resident Type | F1: Dietary Preference | G1: Spice Level | H1: Meal Need (Lunch/Dinner/Both) | I1: Family Size | J1: Preferred Delivery Time | K1: First Order Date | L1: Last Order Date | M1: Total Orders | N1: Total Spent (₹) | O1: Avg Order Value (₹) | P1: Days Between Orders | Q1: Repeat Customer | R1: Source | S1: Referrer | T1: Likely to Recommend (1-5) | U1: Important Factors | V1: Language | W1: Notes
